{
  "id": "photos__nyu-shanghai-class-2023-reception-new-york-d225bbb36f",
  "url": "https://shanghai.nyu.edu/photos/nyu-shanghai-class-2023-reception-new-york?page=1",
  "canonical_url": "https://shanghai.nyu.edu/photos/nyu-shanghai-class-2023-reception-new-york",
  "page_type": "photos",
  "title": "NYU Shanghai Class of 2023 Reception in New York",
  "description": "",
  "language": "en",
  "published_time": "",
  "modified_time": "",
  "sitemap_lastmod": null,
  "text": "NYU Shanghai Class of 2023 Reception in New York\nTwitter\nFacebook\nWeibo",
  "text_blocks": [
    {
      "type": "h1",
      "text": "NYU Shanghai Class of 2023 Reception in New York"
    },
    {
      "type": "li",
      "text": "Twitter"
    },
    {
      "type": "li",
      "text": "Facebook"
    },
    {
      "type": "li",
      "text": "Weibo"
    }
  ],
  "images": [
    {
      "url": "https://cdn.shanghai.nyu.edu/sites/default/files/styles/gallery_list__580x250/public/field/album_picture/02_1.jpg?itok=vlhJFR2V",
      "alt": "NYU Shanghai Commencement 2021",
      "caption": "",
      "source": "img",
      "local_path": "_shared/02_1-780984d914ed.jpg",
      "download_status": "downloaded",
      "bytes": 37238,
      "content_type": "image/jpeg"
    },
    {
      "url": "https://cdn.shanghai.nyu.edu/sites/default/files/styles/gallery_list__580x250/public/field/album_picture/1_4.jpg?itok=C_SSv5k0",
      "alt": "Class of 2021 Go Local Master’s Convocation",
      "caption": "",
      "source": "img",
      "local_path": "",
      "download_status": "error",
      "error": "HTTPSConnectionPool(host='cdn.shanghai.nyu.edu', port=443): Read timed out. (read timeout=20)"
    },
    {
      "url": "https://cdn.shanghai.nyu.edu/sites/default/files/styles/gallery_list__580x250/public/field/album_picture/1._banner_0.jpeg?itok=v_CdBUQk",
      "alt": "Full orchestra salutes camera",
      "caption": "",
      "source": "img",
      "local_path": "_shared/1._banner_0-aedca456afcd.jpeg",
      "download_status": "downloaded",
      "bytes": 41678,
      "content_type": "image/jpeg"
    },
    {
      "url": "https://cdn.shanghai.nyu.edu/sites/default/files/styles/gallery_list__580x250/public/field/album_picture/_fb_0958_1.jpg?itok=ZHxSLBw_",
      "alt": "Group photo of speakers and organizers",
      "caption": "",
      "source": "img",
      "local_path": "_shared/fb_0958_1-cac9856fd303.jpg",
      "download_status": "downloaded",
      "bytes": 24485,
      "content_type": "image/jpeg"
    },
    {
      "url": "https://cdn.shanghai.nyu.edu/sites/default/files/styles/gallery_list__580x250/public/field/album_picture/1_3.jpg?itok=SzL2xkw8",
      "alt": "The Shows Must Go On",
      "caption": "",
      "source": "img",
      "local_path": "",
      "download_status": "error",
      "error": "HTTPSConnectionPool(host='cdn.shanghai.nyu.edu', port=443): Read timed out. (read timeout=20)"
    },
    {
      "url": "https://cdn.shanghai.nyu.edu/sites/default/files/styles/gallery_list__580x250/public/field/album_picture/chamomile_header.jpg?itok=mYp6uuYp",
      "alt": "One in 24 filmmaking challenge",
      "caption": "",
      "source": "img",
      "local_path": "_shared/chamomile_header-5a08a6002f36.jpg",
      "download_status": "downloaded",
      "bytes": 28698,
      "content_type": "image/jpeg"
    },
    {
      "url": "https://cdn.shanghai.nyu.edu/sites/default/files/styles/gallery_list__580x250/public/field/album_picture/movein2020-01.jpg?itok=J8S93nnH",
      "alt": "move in",
      "caption": "",
      "source": "img",
      "local_path": "",
      "download_status": "error",
      "error": "HTTPSConnectionPool(host='cdn.shanghai.nyu.edu', port=443): Read timed out. (read timeout=20)"
    },
    {
      "url": "https://cdn.shanghai.nyu.edu/sites/default/files/styles/gallery_list__580x250/public/field/album_picture/behind01.jpg?itok=LtA7Vk-7",
      "alt": "Behind the Shadows and Symmetry",
      "caption": "",
      "source": "img",
      "local_path": "_shared/behind01-bf664c0cc423.jpg",
      "download_status": "downloaded",
      "bytes": 14065,
      "content_type": "image/jpeg"
    },
    {
      "url": "https://cdn.shanghai.nyu.edu/sites/default/files/styles/gallery_list__580x250/public/field/album_picture/1_6.jpg?itok=HEnoZHjy",
      "alt": "Class of 2021 Master’s Convocation",
      "caption": "",
      "source": "img",
      "local_path": "_shared/1_6-0c26d1316da9.jpg",
      "download_status": "downloaded",
      "bytes": 31529,
      "content_type": "image/jpeg"
    },
    {
      "url": "https://cdn.shanghai.nyu.edu/sites/default/files/styles/gallery_list__580x250/public/field/album_picture/yuan_1.jpg?itok=cc2HBvfT",
      "alt": "Eric Ling Symmetry",
      "caption": "",
      "source": "img",
      "local_path": "_shared/yuan_1-8c08696f724e.jpg",
      "download_status": "downloaded",
      "bytes": 35973,
      "content_type": "image/jpeg"
    },
    {
      "url": "https://cdn.shanghai.nyu.edu/sites/default/files/styles/gallery_list__580x250/public/field/album_picture/eoss19-01.jpg?itok=C2OeWQIw",
      "alt": "End of Semester Show 2019",
      "caption": "",
      "source": "img",
      "local_path": "_shared/eoss19-01-55521cc2a93b.jpg",
      "download_status": "downloaded",
      "bytes": 25337,
      "content_type": "image/jpeg"
    },
    {
      "url": "https://cdn.shanghai.nyu.edu/sites/default/files/styles/gallery_list__580x250/public/field/album_picture/nyu07950.jpg?itok=jJvuPRCs",
      "alt": "Yangjing Neighborhood Tour",
      "caption": "",
      "source": "img",
      "local_path": "_shared/nyu07950-54554036703c.jpg",
      "download_status": "downloaded",
      "bytes": 27724,
      "content_type": "image/jpeg"
    },
    {
      "url": "https://cdn.shanghai.nyu.edu/sites/default/files/styles/gallery_list__580x250/public/field/album_picture/h01.jpg?itok=3GwgET-Z",
      "alt": "A haunted house, a screaming room, lip-sync battles--welcome to NYU Shanghai's \"Carnival of Terrors\"",
      "caption": "",
      "source": "img",
      "local_path": "_shared/h01-b6e38ac86bbd.jpg",
      "download_status": "downloaded",
      "bytes": 33411,
      "content_type": "image/jpeg"
    },
    {
      "url": "https://cdn.shanghai.nyu.edu/sites/default/files/styles/gallery_list__580x250/public/field/album_picture/2019-ally-week01.jpg?itok=gohTKfbK",
      "alt": "Ally Week 2019",
      "caption": "",
      "source": "img",
      "local_path": "_shared/2019-ally-week01-5e329a178362.jpg",
      "download_status": "downloaded",
      "bytes": 21645,
      "content_type": "image/jpeg"
    },
    {
      "url": "https://cdn.shanghai.nyu.edu/sites/default/files/styles/gallery_list__580x250/public/field/album_picture/reality-2019-01_0.jpg?itok=QUQXQW6r",
      "alt": "Reality 2019",
      "caption": "",
      "source": "img",
      "local_path": "_shared/reality-2019-01_0-5c6803435e58.jpg",
      "download_status": "downloaded",
      "bytes": 26915,
      "content_type": "image/jpeg"
    }
  ],
  "links": [
    {
      "url": "https://cdn.shanghai.nyu.edu/sites/default/files/field/album_picture/1_nyu_reception.jpg",
      "text": "",
      "internal": false
    },
    {
      "url": "https://cdn.shanghai.nyu.edu/sites/default/files/field/album_picture/2_nyu_reception.jpg",
      "text": "",
      "internal": false
    },
    {
      "url": "https://cdn.shanghai.nyu.edu/sites/default/files/field/album_picture/3_nyu_reception.jpg",
      "text": "",
      "internal": false
    },
    {
      "url": "https://cdn.shanghai.nyu.edu/sites/default/files/field/album_picture/4_nyu_reception.jpg",
      "text": "",
      "internal": false
    },
    {
      "url": "https://cdn.shanghai.nyu.edu/sites/default/files/field/album_picture/5_nyu_reception.jpg",
      "text": "",
      "internal": false
    },
    {
      "url": "https://cdn.shanghai.nyu.edu/sites/default/files/field/album_picture/6_nyu_reception.jpg",
      "text": "",
      "internal": false
    },
    {
      "url": "https://cdn.shanghai.nyu.edu/sites/default/files/field/album_picture/7_nyu_reception.jpg",
      "text": "",
      "internal": false
    },
    {
      "url": "https://cdn.shanghai.nyu.edu/sites/default/files/field/album_picture/8_nyu_reception.jpg",
      "text": "",
      "internal": false
    },
    {
      "url": "https://cdn.shanghai.nyu.edu/sites/default/files/field/album_picture/9_nyu_reception.jpg",
      "text": "",
      "internal": false
    },
    {
      "url": "https://cdn.shanghai.nyu.edu/sites/default/files/field/album_picture/10_nyu_reception.jpg",
      "text": "",
      "internal": false
    },
    {
      "url": "https://cdn.shanghai.nyu.edu/sites/default/files/field/album_picture/11_nyu_reception.jpg",
      "text": "",
      "internal": false
    },
    {
      "url": "https://cdn.shanghai.nyu.edu/sites/default/files/field/album_picture/12_nyu_reception.jpg",
      "text": "",
      "internal": false
    },
    {
      "url": "https://cdn.shanghai.nyu.edu/sites/default/files/field/album_picture/13_nyu_reception.jpg",
      "text": "",
      "internal": false
    },
    {
      "url": "https://cdn.shanghai.nyu.edu/sites/default/files/field/album_picture/14_nyu_reception.jpg",
      "text": "",
      "internal": false
    },
    {
      "url": "https://cdn.shanghai.nyu.edu/sites/default/files/field/album_picture/15_nyu_reception.jpg",
      "text": "",
      "internal": false
    },
    {
      "url": "https://cdn.shanghai.nyu.edu/sites/default/files/field/album_picture/16_nyu_reception.jpg",
      "text": "",
      "internal": false
    },
    {
      "url": "https://cdn.shanghai.nyu.edu/sites/default/files/field/album_picture/17_nyu_reception.jpg",
      "text": "",
      "internal": false
    },
    {
      "url": "https://cdn.shanghai.nyu.edu/sites/default/files/field/album_picture/18_nyu_reception.jpg",
      "text": "",
      "internal": false
    },
    {
      "url": "https://cdn.shanghai.nyu.edu/sites/default/files/field/album_picture/19_nyu_reception.jpg",
      "text": "",
      "internal": false
    },
    {
      "url": "https://cdn.shanghai.nyu.edu/sites/default/files/field/album_picture/20_nyu_reception.jpg",
      "text": "",
      "internal": false
    },
    {
      "url": "https://cdn.shanghai.nyu.edu/sites/default/files/field/album_picture/21_nyu_reception.jpg",
      "text": "",
      "internal": false
    },
    {
      "url": "https://cdn.shanghai.nyu.edu/sites/default/files/field/album_picture/22_nyu_reception.jpg",
      "text": "",
      "internal": false
    },
    {
      "url": "https://cdn.shanghai.nyu.edu/sites/default/files/field/album_picture/23_nyu_reception.jpg",
      "text": "",
      "internal": false
    },
    {
      "url": "https://cdn.shanghai.nyu.edu/sites/default/files/field/album_picture/24_nyu_reception.jpg",
      "text": "",
      "internal": false
    },
    {
      "url": "https://cdn.shanghai.nyu.edu/sites/default/files/field/album_picture/25_nyu_reception.jpg",
      "text": "",
      "internal": false
    },
    {
      "url": "https://cdn.shanghai.nyu.edu/sites/default/files/field/album_picture/26_nyu_reception.jpg",
      "text": "",
      "internal": false
    },
    {
      "url": "https://cdn.shanghai.nyu.edu/sites/default/files/field/album_picture/27_nyu_reception_0.jpg",
      "text": "",
      "internal": false
    },
    {
      "url": "https://cdn.shanghai.nyu.edu/sites/default/files/field/album_picture/28_nyu_reception.jpg",
      "text": "",
      "internal": false
    },
    {
      "url": "https://twitter.com/intent/tweet?text=NYU%20Shanghai%20Class%20of%202023%20Reception%20in%20New%20York&url=https%3A//shanghai.nyu.edu/photos/nyu-shanghai-class-2023-reception-new-york&status=NYU%20Shanghai%20Class%20of%202023%20Reception%20in%20New%20York%20https%3A//shanghai.nyu.edu/photos/nyu-shanghai-class-2023-reception-new-york",
      "text": "Twitter",
      "internal": false
    },
    {
      "url": "https://www.facebook.com/share.php?u=https%3A//shanghai.nyu.edu/photos/nyu-shanghai-class-2023-reception-new-york&title=NYU%20Shanghai%20Class%20of%202023%20Reception%20in%20New%20York",
      "text": "Facebook",
      "internal": false
    },
    {
      "url": "http://service.weibo.com/share/share.php?url=https%3A//shanghai.nyu.edu/photos/nyu-shanghai-class-2023-reception-new-york&title=NYU%20Shanghai%20Class%20of%202023%20Reception%20in%20New%20York",
      "text": "Weibo",
      "internal": false
    },
    {
      "url": "https://shanghai.nyu.edu/photos/nyu-shanghai-commencement-2021",
      "text": "",
      "internal": true
    },
    {
      "url": "https://shanghai.nyu.edu/photos/class-2021-go-local-masters-convocation",
      "text": "",
      "internal": true
    },
    {
      "url": "https://shanghai.nyu.edu/photos/nyu-shanghais-2021-spring-concert",
      "text": "",
      "internal": true
    },
    {
      "url": "https://shanghai.nyu.edu/photos/tedxnyushanghai-presents-flip-side",
      "text": "",
      "internal": true
    },
    {
      "url": "https://shanghai.nyu.edu/photos/show-and-tell-arts-students-present-their-semesters-labors",
      "text": "",
      "internal": true
    },
    {
      "url": "https://shanghai.nyu.edu/photos/shanghai-through-filmmakers-lens",
      "text": "",
      "internal": true
    },
    {
      "url": "https://shanghai.nyu.edu/photos/welcome-class-2024",
      "text": "",
      "internal": true
    },
    {
      "url": "https://shanghai.nyu.edu/photos/behind-shadows-and-symmetry",
      "text": "",
      "internal": true
    },
    {
      "url": "https://shanghai.nyu.edu/photos/class-2021-masters-convocation",
      "text": "",
      "internal": true
    },
    {
      "url": "https://shanghai.nyu.edu/photos/photo-gallery-back-school-and-preparing-commencement",
      "text": "",
      "internal": true
    },
    {
      "url": "https://shanghai.nyu.edu/photos/end-semester-show-2019",
      "text": "",
      "internal": true
    },
    {
      "url": "https://shanghai.nyu.edu/photos/yangjing-neighborhood-tour",
      "text": "",
      "internal": true
    },
    {
      "url": "https://shanghai.nyu.edu/photos/carnival-terrors",
      "text": "",
      "internal": true
    },
    {
      "url": "https://shanghai.nyu.edu/photos/ally-week-2019",
      "text": "",
      "internal": true
    },
    {
      "url": "https://shanghai.nyu.edu/photos/scenes-songs-and-dose-reality",
      "text": "",
      "internal": true
    }
  ],
  "word_count_estimate": 12,
  "crawled_at": "2026-06-09T04:52:29+00:00",
  "sequence": 2293
}